xlnpwmon/__init__.py
xlnpwmon/_core.cpython-312-aarch64-linux-gnu.so
xlnpwmon/cli.py
xlnpwmon-0.0.3.dist-info/METADATA
xlnpwmon-0.0.3.dist-info/WHEEL
xlnpwmon-0.0.3.dist-info/top_level.txt
xlnpwmon-0.0.3.dist-info/RECORD
xlnpwmon-0.0.3.dist-info/licenses/LICENSE
