Metadata-Version: 2.1
Name: xlnpwmon
Version: 0.0.3
Summary: A simple power monitor for Xilinx
Author: Qi Deng
Author-email: Qi Deng <dengqi935@gmail.com>
Keywords: xilinx,power,monitor,nvidia,nvidia-xilinx,xilinx-power-monitor
Requires-Python: >=3.8
License-File: LICENSE
Requires-Dist: pybind11>=2.9.0
Provides-Extra: cli
Requires-Dist: rich>=13.9.4; extra == "cli"
Provides-Extra: dev
Requires-Dist: pytest>=8.3.5; extra == "dev"
Requires-Dist: black>=24.1.0; extra == "dev"
Requires-Dist: build>=0.10.0; extra == "dev"
Requires-Dist: pyyaml>=6.0.2; extra == "dev"
Requires-Dist: lark>=1.2.2; extra == "dev"
